dockyard_cli/__init__.py
dockyard_cli/login.py
dockyard_cli/main.py
dockyard_cli/metrics.py
dockyard_cli/pcluster.py
dockyard_cli/utils.py
dockyard_cli/workspace.py
dockyard_cli-0.1.16.dist-info/WHEEL
dockyard_cli-0.1.16.dist-info/entry_points.txt
dockyard_cli-0.1.16.dist-info/METADATA
dockyard_cli-0.1.16.dist-info/RECORD
