Metadata-Version: 2.1
Name: dockyard-cli
Version: 0.1.16
Summary: CLI for dockyard
Author: rsingh
Author-email: rsingh@altoslabs.com
Requires-Python: >=3.8,<4.0
Classifier: Programming Language :: Python :: 3
Classifier: Programming Language :: Python :: 3.8
Classifier: Programming Language :: Python :: 3.9
Classifier: Programming Language :: Python :: 3.10
Classifier: Programming Language :: Python :: 3.11
Requires-Dist: click (>=8.1.3,<9.0.0)
Requires-Dist: requests (>=2.28.1,<3.0.0)
Requires-Dist: rich (>=13.3.3,<14.0.0)
Requires-Dist: selenium (>=4.7.2,<5.0.0)
Requires-Dist: sseclient-py (>=1.7.2,<2.0.0)
Requires-Dist: tabulate (>=0.9.0,<0.10.0)
Requires-Dist: webdriver-setup (>=1.1.0,<2.0.0)
